{
	"configurations" : 
	[
		{
			"directories" : 
			[
				{
					"build" : ".",
					"childIndexes" : 
					[
						1,
						2,
						3
					],
					"hasInstallRule" : true,
					"jsonFile" : "directory-.-Debug-f5ebdc15457944623624.json",
					"minimumCMakeVersion" : 
					{
						"string" : "3.10"
					},
					"projectIndex" : 0,
					"source" : ".",
					"targetIndexes" : 
					[
						28
					]
				},
				{
					"build" : "libs/sol2",
					"hasInstallRule" : true,
					"jsonFile" : "directory-libs.sol2-Debug-63463ed0620d3ba266aa.json",
					"minimumCMakeVersion" : 
					{
						"string" : "3.16.0"
					},
					"parentIndex" : 0,
					"projectIndex" : 1,
					"source" : "libs/sol2",
					"targetIndexes" : 
					[
						0,
						1,
						2,
						3,
						4,
						5,
						6,
						7,
						8,
						9,
						10,
						11,
						12,
						13,
						14,
						15,
						16,
						17,
						18,
						19,
						20,
						21,
						22,
						23,
						24,
						25,
						26,
						27
					]
				},
				{
					"build" : "libs/glm",
					"jsonFile" : "directory-libs.glm-Debug-44c86d80c1bd93f510b3.json",
					"minimumCMakeVersion" : 
					{
						"string" : "3.10"
					},
					"parentIndex" : 0,
					"projectIndex" : 0,
					"source" : "libs/glm"
				},
				{
					"build" : "libs/toml",
					"hasInstallRule" : true,
					"jsonFile" : "directory-libs.toml-Debug-10c9140ac9f3415cf939.json",
					"minimumCMakeVersion" : 
					{
						"string" : "3.5"
					},
					"parentIndex" : 0,
					"projectIndex" : 2,
					"source" : "libs/toml"
				}
			],
			"name" : "Debug",
			"projects" : 
			[
				{
					"childIndexes" : 
					[
						1,
						2
					],
					"directoryIndexes" : 
					[
						0,
						2
					],
					"name" : "game",
					"targetIndexes" : 
					[
						28
					]
				},
				{
					"directoryIndexes" : 
					[
						1
					],
					"name" : "sol2",
					"parentIndex" : 0,
					"targetIndexes" : 
					[
						0,
						1,
						2,
						3,
						4,
						5,
						6,
						7,
						8,
						9,
						10,
						11,
						12,
						13,
						14,
						15,
						16,
						17,
						18,
						19,
						20,
						21,
						22,
						23,
						24,
						25,
						26,
						27
					]
				},
				{
					"directoryIndexes" : 
					[
						3
					],
					"name" : "toml11",
					"parentIndex" : 0
				}
			],
			"targets" : 
			[
				{
					"directoryIndex" : 1,
					"id" : "Continuous::@20f9fd3ff3894b321b08",
					"jsonFile" : "target-Continuous-Debug-2cd11dd79d8ffbd97923.json",
					"name" : "Continuous",
					"projectIndex" : 1
				},
				{
					"directoryIndex" : 1,
					"id" : "ContinuousBuild::@20f9fd3ff3894b321b08",
					"jsonFile" : "target-ContinuousBuild-Debug-4d326d93ec7936a1b2e9.json",
					"name" : "ContinuousBuild",
					"projectIndex" : 1
				},
				{
					"directoryIndex" : 1,
					"id" : "ContinuousConfigure::@20f9fd3ff3894b321b08",
					"jsonFile" : "target-ContinuousConfigure-Debug-c20aa819c1f494aca53f.json",
					"name" : "ContinuousConfigure",
					"projectIndex" : 1
				},
				{
					"directoryIndex" : 1,
					"id" : "ContinuousCoverage::@20f9fd3ff3894b321b08",
					"jsonFile" : "target-ContinuousCoverage-Debug-a0453a93160a8dbf07c0.json",
					"name" : "ContinuousCoverage",
					"projectIndex" : 1
				},
				{
					"directoryIndex" : 1,
					"id" : "ContinuousMemCheck::@20f9fd3ff3894b321b08",
					"jsonFile" : "target-ContinuousMemCheck-Debug-1204da71b539bda30f1d.json",
					"name" : "ContinuousMemCheck",
					"projectIndex" : 1
				},
				{
					"directoryIndex" : 1,
					"id" : "ContinuousStart::@20f9fd3ff3894b321b08",
					"jsonFile" : "target-ContinuousStart-Debug-bfc652846f3c9e6d2244.json",
					"name" : "ContinuousStart",
					"projectIndex" : 1
				},
				{
					"directoryIndex" : 1,
					"id" : "ContinuousSubmit::@20f9fd3ff3894b321b08",
					"jsonFile" : "target-ContinuousSubmit-Debug-cb1db2323d14c76769fe.json",
					"name" : "ContinuousSubmit",
					"projectIndex" : 1
				},
				{
					"directoryIndex" : 1,
					"id" : "ContinuousTest::@20f9fd3ff3894b321b08",
					"jsonFile" : "target-ContinuousTest-Debug-2db0cbd4fce9d258a1b8.json",
					"name" : "ContinuousTest",
					"projectIndex" : 1
				},
				{
					"directoryIndex" : 1,
					"id" : "ContinuousUpdate::@20f9fd3ff3894b321b08",
					"jsonFile" : "target-ContinuousUpdate-Debug-f48873cba9b805b834cc.json",
					"name" : "ContinuousUpdate",
					"projectIndex" : 1
				},
				{
					"directoryIndex" : 1,
					"id" : "Experimental::@20f9fd3ff3894b321b08",
					"jsonFile" : "target-Experimental-Debug-a114026fcddb75bec20b.json",
					"name" : "Experimental",
					"projectIndex" : 1
				},
				{
					"directoryIndex" : 1,
					"id" : "ExperimentalBuild::@20f9fd3ff3894b321b08",
					"jsonFile" : "target-ExperimentalBuild-Debug-04db08753842b22d6fef.json",
					"name" : "ExperimentalBuild",
					"projectIndex" : 1
				},
				{
					"directoryIndex" : 1,
					"id" : "ExperimentalConfigure::@20f9fd3ff3894b321b08",
					"jsonFile" : "target-ExperimentalConfigure-Debug-19aab10d4a9c465b0fe7.json",
					"name" : "ExperimentalConfigure",
					"projectIndex" : 1
				},
				{
					"directoryIndex" : 1,
					"id" : "ExperimentalCoverage::@20f9fd3ff3894b321b08",
					"jsonFile" : "target-ExperimentalCoverage-Debug-dc4d8d5ff058f6717fb9.json",
					"name" : "ExperimentalCoverage",
					"projectIndex" : 1
				},
				{
					"directoryIndex" : 1,
					"id" : "ExperimentalMemCheck::@20f9fd3ff3894b321b08",
					"jsonFile" : "target-ExperimentalMemCheck-Debug-d37f6ee0d8d363df7fb1.json",
					"name" : "ExperimentalMemCheck",
					"projectIndex" : 1
				},
				{
					"directoryIndex" : 1,
					"id" : "ExperimentalStart::@20f9fd3ff3894b321b08",
					"jsonFile" : "target-ExperimentalStart-Debug-78550375cd61e31258dc.json",
					"name" : "ExperimentalStart",
					"projectIndex" : 1
				},
				{
					"directoryIndex" : 1,
					"id" : "ExperimentalSubmit::@20f9fd3ff3894b321b08",
					"jsonFile" : "target-ExperimentalSubmit-Debug-ee464a2cb3bcacc408aa.json",
					"name" : "ExperimentalSubmit",
					"projectIndex" : 1
				},
				{
					"directoryIndex" : 1,
					"id" : "ExperimentalTest::@20f9fd3ff3894b321b08",
					"jsonFile" : "target-ExperimentalTest-Debug-88e09438b24ecd5463ce.json",
					"name" : "ExperimentalTest",
					"projectIndex" : 1
				},
				{
					"directoryIndex" : 1,
					"id" : "ExperimentalUpdate::@20f9fd3ff3894b321b08",
					"jsonFile" : "target-ExperimentalUpdate-Debug-64ad16dea42d7ad642b4.json",
					"name" : "ExperimentalUpdate",
					"projectIndex" : 1
				},
				{
					"directoryIndex" : 1,
					"id" : "Nightly::@20f9fd3ff3894b321b08",
					"jsonFile" : "target-Nightly-Debug-53dc1b8207138d000272.json",
					"name" : "Nightly",
					"projectIndex" : 1
				},
				{
					"directoryIndex" : 1,
					"id" : "NightlyBuild::@20f9fd3ff3894b321b08",
					"jsonFile" : "target-NightlyBuild-Debug-85529b5fa61372d8085a.json",
					"name" : "NightlyBuild",
					"projectIndex" : 1
				},
				{
					"directoryIndex" : 1,
					"id" : "NightlyConfigure::@20f9fd3ff3894b321b08",
					"jsonFile" : "target-NightlyConfigure-Debug-d3e77edfb0386371734e.json",
					"name" : "NightlyConfigure",
					"projectIndex" : 1
				},
				{
					"directoryIndex" : 1,
					"id" : "NightlyCoverage::@20f9fd3ff3894b321b08",
					"jsonFile" : "target-NightlyCoverage-Debug-6cbc52bac4d5fc862f52.json",
					"name" : "NightlyCoverage",
					"projectIndex" : 1
				},
				{
					"directoryIndex" : 1,
					"id" : "NightlyMemCheck::@20f9fd3ff3894b321b08",
					"jsonFile" : "target-NightlyMemCheck-Debug-d5cf3be6759b8bede202.json",
					"name" : "NightlyMemCheck",
					"projectIndex" : 1
				},
				{
					"directoryIndex" : 1,
					"id" : "NightlyMemoryCheck::@20f9fd3ff3894b321b08",
					"jsonFile" : "target-NightlyMemoryCheck-Debug-dd743c2ad9be18638b57.json",
					"name" : "NightlyMemoryCheck",
					"projectIndex" : 1
				},
				{
					"directoryIndex" : 1,
					"id" : "NightlyStart::@20f9fd3ff3894b321b08",
					"jsonFile" : "target-NightlyStart-Debug-f157ca94e4eb18778a29.json",
					"name" : "NightlyStart",
					"projectIndex" : 1
				},
				{
					"directoryIndex" : 1,
					"id" : "NightlySubmit::@20f9fd3ff3894b321b08",
					"jsonFile" : "target-NightlySubmit-Debug-23fa80bc95b1cba5274e.json",
					"name" : "NightlySubmit",
					"projectIndex" : 1
				},
				{
					"directoryIndex" : 1,
					"id" : "NightlyTest::@20f9fd3ff3894b321b08",
					"jsonFile" : "target-NightlyTest-Debug-f876ba067f5ac613adf8.json",
					"name" : "NightlyTest",
					"projectIndex" : 1
				},
				{
					"directoryIndex" : 1,
					"id" : "NightlyUpdate::@20f9fd3ff3894b321b08",
					"jsonFile" : "target-NightlyUpdate-Debug-a3c228938d8a3ea98825.json",
					"name" : "NightlyUpdate",
					"projectIndex" : 1
				},
				{
					"directoryIndex" : 0,
					"id" : "game::@6890427a1f51a3e7e1df",
					"jsonFile" : "target-game-Debug-d4aa938ed7f856e7b646.json",
					"name" : "game",
					"projectIndex" : 0
				}
			]
		}
	],
	"kind" : "codemodel",
	"paths" : 
	{
		"build" : "/home/dregos/uni/grapevine/cmake-build-debug",
		"source" : "/home/dregos/uni/grapevine"
	},
	"version" : 
	{
		"major" : 2,
		"minor" : 7
	}
}
